qt3utils/__init__.py
qt3utils/errors.py
qt3utils/amplifiers/__init__.py
qt3utils/amplifiers/minicircuits.py
qt3utils/applications/__init__.py
qt3utils/applications/controllers/__init__.py
qt3utils/applications/controllers/nidaq_edge_counter.yaml
qt3utils/applications/controllers/nidaqedgecounter.py
qt3utils/applications/controllers/nidaqpiezocontroller.py
qt3utils/applications/controllers/princeton_spectrometer.py
qt3utils/applications/controllers/princeton_spectrometer.yaml
qt3utils/applications/controllers/random_data_generator.py
qt3utils/applications/controllers/random_data_generator.yaml
qt3utils/applications/controllers/random_spectrometer.yaml
qt3utils/applications/qt3pb/main.py
qt3utils/applications/qt3scan/__init__.py
qt3utils/applications/qt3scan/controller.py
qt3utils/applications/qt3scan/interface.py
qt3utils/applications/qt3scan/main.py
qt3utils/applications/qt3scope/__init__.py
qt3utils/applications/qt3scope/interface.py
qt3utils/applications/qt3scope/main.py
qt3utils/datagenerators/__init__.py
qt3utils/datagenerators/daqsamplers.py
qt3utils/datagenerators/piezoscanner.py
qt3utils/datagenerators/spectrometers/__init__.py
qt3utils/datagenerators/spectrometers/princeton.py
qt3utils/datagenerators/spectrometers/spectrometer.py
qt3utils/experiments/__init__.py
qt3utils/experiments/common.py
qt3utils/experiments/cwodmr.py
qt3utils/experiments/podmr.py
qt3utils/experiments/rabi.py
qt3utils/experiments/ramsey.py
qt3utils/experiments/t1coherence.py
qt3utils/nidaq/__init__.py
qt3utils/nidaq/config.py
qt3utils/pulsers/__init__.py
qt3utils/pulsers/interface.py
qt3utils/pulsers/pulseblaster.py
qt3utils/pulsers/qcsapphire.py
qt3utils-1.1.1.dist-info/LICENSE
qt3utils-1.1.1.dist-info/METADATA
qt3utils-1.1.1.dist-info/WHEEL
qt3utils-1.1.1.dist-info/entry_points.txt
qt3utils-1.1.1.dist-info/top_level.txt
qt3utils-1.1.1.dist-info/RECORD
