Metadata-Version: 2.1
Name: qt3utils
Version: 1.1.1
Summary: A package for performing experiments in the QT3 lab at UW.
Author-email: "G. Adam Cox" <gadamc@gmail.com>
Maintainer-email: "G. Adam Cox" <gadamc@gmail.com>, Maxwell Parsons <mfpars@uw.edu>
License: BSD 3-Clause License
Project-URL: Homepage, https://github.com/qt3uw/qt3utils
Project-URL: Source, https://github.com/qt3uw/qt3utils
Project-URL: Bug Tracker, https://github.com/qt3uw/qt3utils/issues
Project-URL: Changelog, https://github.com/qt3uw/qt3utils/releases
Keywords: qt3,confocal scan,nidaqmx,piezo,stage,control,electron spin control
Classifier: Development Status :: 5 - Production/Stable
Classifier: Intended Audience :: Science/Research
Classifier: Topic :: Scientific/Engineering :: Physics
Classifier: Topic :: Scientific/Engineering
Classifier: License :: OSI Approved :: BSD License
Classifier: Programming Language :: Python :: 3.8
Classifier: Programming Language :: Python :: 3.9
Classifier: Programming Language :: Python :: 3.10
Classifier: Programming Language :: Python :: 3.11
Classifier: Programming Language :: Python :: 3 :: Only
Requires-Python: >=3.8
License-File: LICENSE
Requires-Dist: nidaqmx >=0.6.3
Requires-Dist: numpy >=1.21.2
Requires-Dist: matplotlib >=3.4.3
Requires-Dist: scipy >=1.7.1
Requires-Dist: h5py >=3.3.0
Requires-Dist: qcsapphire >=1.0.1
Requires-Dist: qt3rfsynthcontrol >=1.0.1
Requires-Dist: nipiezojenapy >=1.0.4
Requires-Dist: pulseblaster >=1.0.1
Requires-Dist: PyYAML >=6.0.1
Requires-Dist: pythonnet >=3.0.3
